pramanpatram/__init__.py
pramanpatram/pramanpatram.py
pramanpatram-1.0.1.dist-info/LICENSE
pramanpatram-1.0.1.dist-info/METADATA
pramanpatram-1.0.1.dist-info/WHEEL
pramanpatram-1.0.1.dist-info/top_level.txt
pramanpatram-1.0.1.dist-info/RECORD
