Metadata-Version: 2.1
Name: pramanpatram
Version: 1.0.1
Summary: A Python Library to generate event certificates
Home-page: https://github.com/SpaciousCoder78/pramanpatram-lib
Author: Aryan Karamtoth
Author-email: Aryan Karamtoth <aryankmmiv@outlook.com>
License: MIT License
Project-URL: Homepage, https://github.com/SpaciousCoder78/pramanpatram-lib
Project-URL: Issues, https://github.com/SpaciousCoder78/pramanpatram-lib/issues
Classifier: Programming Language :: Python :: 3
Classifier: License :: OSI Approved :: MIT License
Classifier: Operating System :: OS Independent
Requires-Python: >=3.12
License-File: LICENSE
Requires-Dist: pandas
Requires-Dist: PIL
Requires-Dist: pillow
Requires-Dist: textwrap
